matly/__init__.py
matly/matly.py
matly-0.1.1.dist-info/METADATA
matly-0.1.1.dist-info/WHEEL
matly-0.1.1.dist-info/RECORD
