Metadata-Version: 2.1
Name: matly
Version: 0.1.1
Summary: Matly
Home-page: https://github.com/lunastev/Matly
License: MIT
Author: LunaStev
Author-email: lunastev@gurmstudios.com
Requires-Python: >=3.10,<4.0
Classifier: License :: OSI Approved :: MIT License
Classifier: Programming Language :: Python :: 3
Classifier: Programming Language :: Python :: 3.10
Classifier: Programming Language :: Python :: 3.11
Classifier: Programming Language :: Python :: 3.12
Requires-Dist: beautifulsoup4
Requires-Dist: requests
Project-URL: Repository, https://github.com/lunastev/Matly
